{
	"format_version": "1.21.0",
	"minecraft:geometry": [
		{
			"description": {
				"identifier": "geometry.kruemblegard.cephalari",
				"texture_width": 64,
				"texture_height": 64,
				"visible_bounds_width": 2,
				"visible_bounds_height": 3,
				"visible_bounds_offset": [0, 1.5, 0]
			},
			"bones": [
				{
					"name": "root",
					"pivot": [0, 12, 0]
				},
				{
					"name": "head",
					"parent": "root",
					"pivot": [0, 12, -1.5]
				},
				{
					"name": "shell",
					"parent": "head",
					"pivot": [0, 10.32, -1.92],
					"cubes": [
						{
							"origin": [-2.94, 0.66, -0.6],
							"size": [5.88, 3.36, 0],
							"uv": {
								"north": {"uv": [31, 17], "uv_size": [-7, -4]},
								"east": {"uv": [48, 43], "uv_size": [0, 3]},
								"south": {"uv": [53, 43], "uv_size": [5, 3]},
								"west": {"uv": [53, 43], "uv_size": [0, 3]},
								"up": {"uv": [48, 43], "uv_size": [5, 0]},
								"down": {"uv": [53, 43], "uv_size": [5, 0]}
							}
						},
						{
							"origin": [-2.94, 4.02, -1.86],
							"size": [5.88, 4.2, 6.72],
							"uv": {
								"north": {"uv": [15, 2.5], "uv_size": [-7, -2.5]},
								"east": {"uv": [15.05, 8], "uv_size": [7.45, 5]},
								"south": {"uv": [8, 6], "uv_size": [7, 3.5]},
								"west": {"uv": [0, 8], "uv_size": [8, 5]},
								"up": {"uv": [15, 6], "uv_size": [-7, -3.5]},
								"down": {"uv": [17, 13], "uv_size": [7, 10]}
							}
						},
						{
							"origin": [-2.94, 0.66, -3.54],
							"size": [5.88, 3.36, 8.4],
							"uv": {
								"north": {"uv": [15, 6.5], "uv_size": [7, -6]},
								"east": {"uv": [17, 23], "uv_size": [10.05, 4]},
								"south": {"uv": [8, 9.5], "uv_size": [7, 3.5]},
								"west": {"uv": [0, 23], "uv_size": [10, 4]},
								"up": {"uv": [8, 43], "uv_size": [5, 8]},
								"down": {"uv": [24, 13], "uv_size": [-7, 10]}
							}
						}
					]
				},
				{
					"name": "body2",
					"parent": "head",
					"pivot": [0, 8.43, 1.146],
					"cubes": [
						{
							"origin": [-2.1, 0.6642, -4.086],
							"size": [4.2, 3.36, 0],
							"uv": {
								"north": {"uv": [0, 38], "uv_size": [5, 4]},
								"east": {"uv": [0, 76], "uv_size": [0, 3]},
								"south": {"uv": [2, 53], "uv_size": [4, 3]},
								"west": {"uv": [4, 76], "uv_size": [0, 3]},
								"up": {"uv": [0, 76], "uv_size": [4, 0]},
								"down": {"uv": [4, 76], "uv_size": [4, 0]}
							}
						},
						{
							"origin": [-2.1, 0.6642, -5.766],
							"size": [4.2, 3.36, 5.88],
							"uv": {
								"north": {"uv": [29, 29], "uv_size": [5, 6]},
								"east": {"uv": [1.5, 34], "uv_size": [6.3, 4]},
								"south": {"uv": [53.5, 22.5], "uv_size": [4, 3]},
								"west": {"uv": [11.25, 34], "uv_size": [6.25, 4]},
								"up": {"uv": [7, 28.5], "uv_size": [5, 7.7]},
								"down": {"uv": [7, 36.2], "uv_size": [5, -7.7]}
							}
						}
					]
				},
				{
					"name": "profession_body2",
					"parent": "head",
					"pivot": [0, 8.43, 1.146],
					"cubes": [
						{
							"origin": [-2.1, 0.6642, -4.086],
							"size": [4.2, 3.36, 0],
							"inflate": 0.011,
							"uv": {
								"north": {"uv": [0, 38], "uv_size": [5, 4]},
								"east": {"uv": [0, 76], "uv_size": [0, 3]},
								"south": {"uv": [2, 53], "uv_size": [4, 3]},
								"west": {"uv": [4, 76], "uv_size": [0, 3]},
								"up": {"uv": [0, 76], "uv_size": [4, 0]},
								"down": {"uv": [4, 76], "uv_size": [4, 0]}
							}
						},
						{
							"origin": [-2.1, 0.6642, -5.766],
							"size": [4.2, 3.36, 5.88],
							"inflate": 0.011,
							"uv": {
								"north": {"uv": [29, 29], "uv_size": [5, 6]},
								"east": {"uv": [1.5, 34], "uv_size": [6.3, 4]},
								"south": {"uv": [53.5, 22.5], "uv_size": [4, 3]},
								"west": {"uv": [11.25, 34], "uv_size": [6.25, 4]},
								"up": {"uv": [7, 28.5], "uv_size": [5, 7.7]},
								"down": {"uv": [7, 36.2], "uv_size": [5, -7.7]}
							}
						}
					]
				},
				{
					"name": "upper_mouth",
					"parent": "head",
					"pivot": [0, 9.4842, 4.086],
					"cubes": [
						{
							"origin": [-2.10116, 2.34304, -5.76716],
							"size": [4.20232, 1.68232, 1.68232],
							"inflate": -0.002,
							"uv": {
								"north": {"uv": [34, 35.5], "uv_size": [-5, -3]},
								"east": {"uv": [34, 29], "uv_size": [2, 6]},
								"south": {"uv": [60, 55], "uv_size": [4, 1]},
								"west": {"uv": [36, 29], "uv_size": [-2, 6]},
								"up": {"uv": [34, 37], "uv_size": [-5, -2]},
								"down": {"uv": [34, 32.5], "uv_size": [-5, 2]}
							}
						}
					]
				},
				{
					"name": "inner_mouth",
					"parent": "head",
					"pivot": [0, 8.6442, 4.296],
					"cubes": [
						{
							"origin": [-1.26, 1.5042, -5.766],
							"size": [2.52, 1.68, 1.68],
							"uv": {
								"north": {"uv": [34, 29], "uv_size": [-5, 6.5]},
								"east": {"uv": [34, 29], "uv_size": [2, 6]},
								"south": {"uv": [6.5, 34.5], "uv_size": [5, 4]},
								"west": {"uv": [36, 29], "uv_size": [-2, 6]},
								"up": {"uv": [34, 29], "uv_size": [-5, -2]},
								"down": {"uv": [34, 35], "uv_size": [-5, 2]}
							}
						}
					]
				},
				{
					"name": "lower_mouth",
					"parent": "head",
					"pivot": [0, 7.8042, 4.086],
					"cubes": [
						{
							"origin": [-2.10116, 0.65464, -5.76716],
							"size": [4.20232, 1.68232, 1.68232],
							"inflate": -0.002,
							"uv": {
								"north": {"uv": [34, 32.5], "uv_size": [-5, 3]},
								"east": {"uv": [34, 29], "uv_size": [2, 6]},
								"south": {"uv": [60, 63], "uv_size": [4, 1]},
								"west": {"uv": [36, 29], "uv_size": [-2, 6]},
								"up": {"uv": [34, 32], "uv_size": [-5, -2]},
								"down": {"uv": [34, 35], "uv_size": [-5, 2]}
							}
						}
					]
				},
				{
					"name": "arm_left",
					"parent": "root",
					"pivot": [2.5, 11.4, 2.1]
				},
				{
					"name": "middle_arm_left",
					"parent": "arm_left",
					"pivot": [-0.5, -1.3, -0.3],
					"cubes": [
						{"origin": [1.96361, 2.4, -1.78569], "size": [1.4, 1, 1], "pivot": [2.66361, 2.9, -1.28569], "rotation": [0, 22.5, 0], "uv": [10, 29]}
					]
				},
				{
					"name": "middle_finger_left",
					"parent": "middle_arm_left",
					"pivot": [-0.5, -1.3, -0.3],
					"cubes": [
						{
							"origin": [2.84624, 1.7, -1.32047],
							"size": [3.9, 2.7, 0],
							"pivot": [2.74234, 3.05, -1.34673],
							"rotation": [0, 22.5, 0],
							"uv": {
								"north": {"uv": [30, 29.5], "uv_size": [3, 2]},
								"east": {"uv": [29.5, 29.5], "uv_size": [0, 2]},
								"south": {"uv": [24.9, 31.75], "uv_size": [3.65, -1.75]},
								"west": {"uv": [32.5, 29.5], "uv_size": [0, 2]},
								"up": {"uv": [29.5, 29.5], "uv_size": [3, 0]},
								"down": {"uv": [32.5, 29.5], "uv_size": [3, 0]}
							}
						}
					]
				},
				{
					"name": "arm_left2",
					"parent": "arm_left",
					"pivot": [0.1, 9, 0.75439],
					"cubes": [
						{"origin": [1.02793, 1.40143, -1.83238], "size": [2, 1, 1], "pivot": [2.02793, 1.90143, -1.33238], "rotation": [0, 45, 22.5], "uv": [9, 29]}
					]
				},
				{
					"name": "finger_left",
					"parent": "arm_left2",
					"pivot": [0.1, 9, 0.75439],
					"cubes": [
						{
							"origin": [1.91932, 0.7737, -1.928],
							"size": [4.2, 1.7, 0],
							"pivot": [2.56932, 1.6237, -1.928],
							"rotation": [0, 45, 22.5],
							"uv": {
								"north": {"uv": [29.5, 29.5], "uv_size": [4, 1]},
								"east": {"uv": [29.5, 29.5], "uv_size": [0, 1]},
								"south": {"uv": [26, 30], "uv_size": [2.5, 1.5]},
								"west": {"uv": [33.5, 29.5], "uv_size": [0, 1]},
								"up": {"uv": [29.5, 29.5], "uv_size": [4, 0]},
								"down": {"uv": [33.5, 29.5], "uv_size": [4, 0]}
							}
						}
					]
				},
				{
					"name": "little_arm_left",
					"parent": "arm_left",
					"pivot": [0.6, 9.1, 1.05439],
					"cubes": [
						{"origin": [1.85859, 3.15269, -1.6738], "size": [1.6, 1, 1], "pivot": [2.65859, 3.65269, -1.1738], "rotation": [0, 45, -22.5], "uv": [10, 29]},
						{
							"origin": [1.94654, 3.29623, -1.8102],
							"size": [2.6, 1.2, 0],
							"pivot": [3.24654, 3.89623, -1.8102],
							"rotation": [0, 45, -22.5],
							"uv": {
								"north": {"uv": [29.5, 29.5], "uv_size": [4, 5]},
								"east": {"uv": [29.5, 30], "uv_size": [0, 1]},
								"south": {"uv": [27, 28.5], "uv_size": [1.5, 2]},
								"west": {"uv": [35.5, 37], "uv_size": [0.5, 2]},
								"up": {"uv": [29.5, 30], "uv_size": [2, 0]},
								"down": {"uv": [35.5, 38], "uv_size": [2.5, -1]}
							}
						}
					]
				},
				{
					"name": "arm_right",
					"parent": "root",
					"pivot": [-2.5, 11.4, 2.1]
				},
				{
					"name": "middle_arm_right",
					"parent": "arm_right",
					"pivot": [0.5, -1.3, -0.3],
					"cubes": [
						{"origin": [-3.36361, 2.4, -1.78569], "size": [1.4, 1, 1], "pivot": [-2.66361, 2.9, -1.28569], "rotation": [0, -22.5, 0], "uv": [10, 29], "mirror": true}
					]
				},
				{
					"name": "middle_finger_right",
					"parent": "middle_arm_right",
					"pivot": [0.5, -1.3, -0.3],
					"cubes": [
						{
							"origin": [-6.74624, 1.7, -1.32047],
							"size": [3.9, 2.7, 0],
							"pivot": [-2.74234, 3.05, -1.34673],
							"rotation": [0, -22.5, 0],
							"uv": {
								"north": {"uv": [33, 29.5], "uv_size": [-3, 2]},
								"east": {"uv": [32.5, 29.5], "uv_size": [0, 2]},
								"south": {"uv": [28.55, 31.75], "uv_size": [-3.65, -1.75]},
								"west": {"uv": [29.5, 29.5], "uv_size": [0, 2]},
								"up": {"uv": [32.5, 29.5], "uv_size": [-3, 0]},
								"down": {"uv": [35.5, 29.5], "uv_size": [-3, 0]}
							}
						}
					]
				},
				{
					"name": "arm_right2",
					"parent": "arm_right",
					"pivot": [-0.1, 9, 0.75439],
					"cubes": [
						{"origin": [-3.02793, 1.40143, -1.83238], "size": [2, 1, 1], "pivot": [-2.02793, 1.90143, -1.33238], "rotation": [0, -45, -22.5], "uv": [9, 29], "mirror": true}
					]
				},
				{
					"name": "finger_right",
					"parent": "arm_right2",
					"pivot": [-0.1, 9, 0.75439],
					"cubes": [
						{
							"origin": [-6.11932, 0.7737, -1.928],
							"size": [4.2, 1.7, 0],
							"pivot": [-2.56932, 1.6237, -1.928],
							"rotation": [0, -45, -22.5],
							"uv": {
								"north": {"uv": [33.5, 29.5], "uv_size": [-4, 1]},
								"east": {"uv": [33.5, 29.5], "uv_size": [0, 1]},
								"south": {"uv": [28.5, 30], "uv_size": [-2.5, 1.5]},
								"west": {"uv": [29.5, 29.5], "uv_size": [0, 1]},
								"up": {"uv": [33.5, 29.5], "uv_size": [-4, 0]},
								"down": {"uv": [37.5, 29.5], "uv_size": [-4, 0]}
							}
						}
					]
				},
				{
					"name": "little_arm_right",
					"parent": "arm_right",
					"pivot": [-0.6, 9.1, 1.05439],
					"cubes": [
						{"origin": [-3.45859, 3.15269, -1.6738], "size": [1.6, 1, 1], "pivot": [-2.65859, 3.65269, -1.1738], "rotation": [0, -45, 22.5], "uv": [10, 29], "mirror": true},
						{
							"origin": [-4.54654, 3.29623, -1.8102],
							"size": [2.6, 1.2, 0],
							"pivot": [-3.24654, 3.89623, -1.8102],
							"rotation": [0, -45, 22.5],
							"uv": {
								"north": {"uv": [33.5, 29.5], "uv_size": [-4, 5]},
								"east": {"uv": [36, 37], "uv_size": [-0.5, 2]},
								"south": {"uv": [28.5, 28.5], "uv_size": [-1.5, 2]},
								"west": {"uv": [29.5, 30], "uv_size": [0, 1]},
								"up": {"uv": [31.5, 30], "uv_size": [-2, 0]},
								"down": {"uv": [38, 38], "uv_size": [-2.5, -1]}
							}
						}
					]
				},
				{
					"name": "leg_right",
					"parent": "root",
					"pivot": [-1, 6, 0],
					"cubes": [
						{"origin": [-2, 0.1, 0], "size": [1, 1.3, 1], "uv": [2, 17], "mirror": true}
					]
				},
				{
					"name": "leg_left",
					"parent": "root",
					"pivot": [1, 6, 0],
					"cubes": [
						{"origin": [1, 0.1, 0], "size": [1, 1.3, 1], "uv": [2, 17]}
					]
				}
			]
		}
	]
}