{
  "feature": {
    "type": "minecraft:simple_random_selector",
    "config": {
      "features": [
        { "feature": "kruemblegard:cairn_tree/mega", "placement": [] }
      ]
    }
  },
  "placement": [
    { "type": "minecraft:rarity_filter", "chance": 80 },
    { "type": "minecraft:in_square" },
    { "type": "minecraft:surface_water_depth_filter", "max_water_depth": 0 },
    { "type": "minecraft:heightmap", "heightmap": "MOTION_BLOCKING" },
    {
      "type": "minecraft:block_predicate_filter",
      "predicate": {
        "type": "minecraft:would_survive",
        "state": { "Name": "kruemblegard:cairn_tree_sapling" }
      }
    },
    { "type": "minecraft:biome" }
  ]
}
