{
  "textures": {
    "up": "kruemblegard:block/pressure_conduit_top",
    "down": "kruemblegard:block/pressure_conduit_bottom",
    "north": "kruemblegard:block/pressure_conduit_front_level4",
    "south": "kruemblegard:block/pressure_conduit_side_level4",
    "east": "kruemblegard:block/pressure_conduit_side_level4",
    "west": "kruemblegard:block/pressure_conduit_side_level4",
    "particle": "kruemblegard:block/pressure_conduit_front_level4"
  },
  "elements": [
    {
      "from": [1, 0, 1],
      "to": [15, 3, 15],
      "faces": {
        "north": {"texture": "#south"},
        "south": {"texture": "#south"},
        "east": {"texture": "#east"},
        "west": {"texture": "#west"},
        "up": {"texture": "#down"},
        "down": {"texture": "#down"}
      }
    },
    {
      "from": [4, 4, 4],
      "to": [12, 13, 12],
      "faces": {
        "north": {"texture": "#north"},
        "south": {"texture": "#south"},
        "east": {"texture": "#east"},
        "west": {"texture": "#west"},
        "up": {"texture": "#up"},
        "down": {"texture": "#down"}
      }
    },
    {
      "from": [6, 8, 0],
      "to": [10, 11, 4],
      "faces": {
        "north": {"texture": "#north"},
        "south": {"texture": "#north"},
        "east": {"texture": "#east"},
        "west": {"texture": "#west"},
        "up": {"texture": "#up"},
        "down": {"texture": "#down"}
      }
    },
    {
      "from": [6, 8, 12],
      "to": [10, 11, 16],
      "faces": {
        "north": {"texture": "#south"},
        "south": {"texture": "#south"},
        "east": {"texture": "#east"},
        "west": {"texture": "#west"},
        "up": {"texture": "#up"},
        "down": {"texture": "#down"}
      }
    },
    {
      "from": [12, 8, 6],
      "to": [16, 11, 10],
      "faces": {
        "north": {"texture": "#north"},
        "south": {"texture": "#south"},
        "east": {"texture": "#east"},
        "west": {"texture": "#east"},
        "up": {"texture": "#up"},
        "down": {"texture": "#down"}
      }
    },
    {
      "from": [0, 8, 6],
      "to": [4, 11, 10],
      "faces": {
        "north": {"texture": "#north"},
        "south": {"texture": "#south"},
        "east": {"texture": "#west"},
        "west": {"texture": "#west"},
        "up": {"texture": "#up"},
        "down": {"texture": "#down"}
      }
    },
    {
      "from": [3, 13, 3],
      "to": [13, 15, 13],
      "faces": {
        "north": {"texture": "#up"},
        "south": {"texture": "#up"},
        "east": {"texture": "#up"},
        "west": {"texture": "#up"},
        "up": {"texture": "#up"},
        "down": {"texture": "#down"}
      }
    },
    {
      "from": [2, 5, 2],
      "to": [4, 7, 4],
      "faces": {
        "north": {"texture": "#south"},
        "south": {"texture": "#south"},
        "east": {"texture": "#south"},
        "west": {"texture": "#south"},
        "up": {"texture": "#up"},
        "down": {"texture": "#down"}
      }
    },
    {
      "from": [12, 5, 12],
      "to": [14, 7, 14],
      "faces": {
        "north": {"texture": "#south"},
        "south": {"texture": "#south"},
        "east": {"texture": "#south"},
        "west": {"texture": "#south"},
        "up": {"texture": "#up"},
        "down": {"texture": "#down"}
      }
    }
  ]
}
