{
  "type": "minecraft:block",
  "pools": [
    {
      "rolls": 1,
      "entries": [
        { "type": "minecraft:item", "name": "kruemblegard:soulberry_shrub" }
      ],
      "conditions": [
        {
          "condition": "minecraft:match_tool",
          "predicate": {
            "enchantments": [
              { "enchantment": "minecraft:silk_touch", "levels": { "min": 1 } }
            ]
          }
        }
      ]
    },
    {
      "rolls": 1,
      "entries": [
        { "type": "minecraft:item", "name": "kruemblegard:soulberries" }
      ],
      "conditions": [
        { "condition": "minecraft:survives_explosion" }
      ]
    }
  ]
}
