{
  "kruemblegard_ambient": {
    "subtitle": "subtitles.kruemblegard.ambient",
    "sounds": [
      {"name": "kruemblegard:horror-background-atmosphere-09_universfield", "stream": true}
    ]
  },
  "kruemblegard_death": {
    "subtitle": "subtitles.kruemblegard.death",
    "sounds": [
      {"name": "kruemblegard:horror-background-atmosphere-09_universfield", "stream": true}
    ]
  },
  "kruemblegard_attack": {
    "subtitle": "subtitles.kruemblegard.attack",
    "sounds": [
      {"name": "kruemblegard:horror-background-atmosphere-09_universfield", "stream": true}
    ]
  },
  "kruemblegard_dash": {
    "subtitle": "subtitles.kruemblegard.dash",
    "sounds": [
      {"name": "kruemblegard:horror-background-atmosphere-09_universfield", "stream": true}
    ]
  },
  "kruemblegard_storm": {
    "subtitle": "subtitles.kruemblegard.storm",
    "sounds": [
      {"name": "kruemblegard:horror-background-atmosphere-09_universfield", "stream": true}
    ]
  },
  "kruemblegard.rise": {
    "sounds": [
      {"name": "kruemblegard:horror-background-atmosphere-09_universfield", "stream": true}
    ]
  },
  "kruemblegard.core_hum": {
    "sounds": [
      {"name": "kruemblegard:horror-background-atmosphere-09_universfield", "stream": true}
    ]
  },
  "kruemblegard.attack_smash": {
    "sounds": [
      {"name": "kruemblegard:horror-background-atmosphere-09_universfield", "stream": true}
    ]
  },
  "kruemblegard.attack_slam": {
    "sounds": [
      {"name": "kruemblegard:horror-background-atmosphere-09_universfield", "stream": true}
    ]
  },
  "kruemblegard.attack_rune": {
    "sounds": [
      {"name": "kruemblegard:horror-background-atmosphere-09_universfield", "stream": true}
    ]
  },
  "kruemblegard.radiant": {
    "sounds": [
      {"name": "kruemblegard:horror-background-atmosphere-09_universfield", "stream": true}
    ]
  },
  "music.kruemblegard": {
    "sounds": [
      {"name": "kruemblegard:horror-background-atmosphere-09_universfield", "stream": true}
    ]
  },
  "music.wayfall": {
    "sounds": [
      {"name": "kruemblegard:horror-background-atmosphere-09_universfield", "stream": true}
    ]
  },

  "entity.traprock.sleep_ambient": {
    "subtitle": "subtitles.kruemblegard.traprock.sleep_ambient",
    "sounds": [
      {"name": "kruemblegard:entity/traprock/sleep_ambient"}
    ]
  },
  "entity.traprock.awaken": {
    "subtitle": "subtitles.kruemblegard.traprock.awaken",
    "sounds": [
      {"name": "kruemblegard:entity/traprock/awaken"}
    ]
  },
  "entity.traprock.ambient": {
    "subtitle": "subtitles.kruemblegard.traprock.ambient",
    "sounds": [
      {"name": "kruemblegard:entity/traprock/ambient"}
    ]
  },
  "entity.traprock.hurt": {
    "subtitle": "subtitles.kruemblegard.traprock.hurt",
    "sounds": [
      {"name": "kruemblegard:entity/traprock/hurt"}
    ]
  },
  "entity.traprock.death": {
    "subtitle": "subtitles.kruemblegard.traprock.death",
    "sounds": [
      {"name": "kruemblegard:entity/traprock/death"}
    ]
  },
  "entity.traprock.attack": {
    "subtitle": "subtitles.kruemblegard.traprock.attack",
    "sounds": [
      {"name": "kruemblegard:entity/traprock/attack"}
    ]
  },

  "entity.pebblit.ambient": {
    "subtitle": "subtitles.kruemblegard.pebblit.ambient",
    "sounds": [
      {"name": "kruemblegard:entity/pebblit/ambient"}
    ]
  },
  "entity.pebblit.hurt": {
    "subtitle": "subtitles.kruemblegard.pebblit.hurt",
    "sounds": [
      {"name": "kruemblegard:entity/pebblit/hurt"}
    ]
  },
  "entity.pebblit.death": {
    "subtitle": "subtitles.kruemblegard.pebblit.death",
    "sounds": [
      {"name": "kruemblegard:entity/pebblit/death"}
    ]
  },
  "entity.pebblit.step": {
    "subtitle": "subtitles.kruemblegard.pebblit.step",
    "sounds": [
      {"name": "kruemblegard:entity/pebblit/step"}
    ]
  },
  "entity.pebblit.tame": {
    "subtitle": "subtitles.kruemblegard.pebblit.tame",
    "sounds": [
      {"name": "kruemblegard:entity/pebblit/tame"}
    ]
  },
  "entity.pebblit.perch": {
    "subtitle": "subtitles.kruemblegard.pebblit.perch",
    "sounds": [
      {"name": "kruemblegard:entity/pebblit/perch"}
    ]
  },

  "entity.great_hunger.ambient": {
    "subtitle": "subtitles.kruemblegard.great_hunger.ambient",
    "sounds": [
      {"name": "kruemblegard:entity/great_hunger/ambient"}
    ]
  },
  "entity.great_hunger.hurt": {
    "subtitle": "subtitles.kruemblegard.great_hunger.hurt",
    "sounds": [
      {"name": "kruemblegard:entity/great_hunger/hurt"}
    ]
  },
  "entity.great_hunger.death": {
    "subtitle": "subtitles.kruemblegard.great_hunger.death",
    "sounds": [
      {"name": "kruemblegard:entity/great_hunger/death"}
    ]
  },
  "entity.great_hunger.step": {
    "subtitle": "subtitles.kruemblegard.great_hunger.step",
    "sounds": [
      {"name": "kruemblegard:entity/great_hunger/step"}
    ]
  },
  "entity.great_hunger.bite": {
    "subtitle": "subtitles.kruemblegard.great_hunger.bite",
    "sounds": [
      {"name": "kruemblegard:entity/great_hunger/bite"}
    ]
  },

  "entity.scattered_enderman.ambient": {
    "subtitle": "subtitles.kruemblegard.scattered_enderman.ambient",
    "sounds": [
      {"name": "kruemblegard:entity/scattered_enderman/ambient"}
    ]
  },
  "entity.scattered_enderman.hurt": {
    "subtitle": "subtitles.kruemblegard.scattered_enderman.hurt",
    "sounds": [
      {"name": "kruemblegard:entity/scattered_enderman/hurt"}
    ]
  },
  "entity.scattered_enderman.death": {
    "subtitle": "subtitles.kruemblegard.scattered_enderman.death",
    "sounds": [
      {"name": "kruemblegard:entity/scattered_enderman/death"}
    ]
  },
  "entity.scattered_enderman.teleport": {
    "subtitle": "subtitles.kruemblegard.scattered_enderman.teleport",
    "sounds": [
      {"name": "kruemblegard:entity/scattered_enderman/teleport"}
    ]
  },
  "entity.scattered_enderman.scream": {
    "subtitle": "subtitles.kruemblegard.scattered_enderman.scream",
    "sounds": [
      {"name": "kruemblegard:entity/scattered_enderman/scream"}
    ]
  },

  "entity.fault_crawler.ambient": {
    "subtitle": "subtitles.kruemblegard.fault_crawler.ambient",
    "sounds": [
      {"name": "kruemblegard:entity/fault_crawler/ambient"}
    ]
  },
  "entity.fault_crawler.hurt": {
    "subtitle": "subtitles.kruemblegard.fault_crawler.hurt",
    "sounds": [
      {"name": "kruemblegard:entity/fault_crawler/hurt"}
    ]
  },
  "entity.fault_crawler.death": {
    "subtitle": "subtitles.kruemblegard.fault_crawler.death",
    "sounds": [
      {"name": "kruemblegard:entity/fault_crawler/death"}
    ]
  },
  "entity.fault_crawler.step": {
    "subtitle": "subtitles.kruemblegard.fault_crawler.step",
    "sounds": [
      {"name": "kruemblegard:entity/fault_crawler/step"}
    ]
  },
  "entity.fault_crawler.pulse": {
    "subtitle": "subtitles.kruemblegard.fault_crawler.pulse",
    "sounds": [
      {"name": "kruemblegard:entity/fault_crawler/pulse"}
    ]
  },
  "entity.fault_crawler.slam": {
    "subtitle": "subtitles.kruemblegard.fault_crawler.slam",
    "sounds": [
      {"name": "kruemblegard:entity/fault_crawler/slam"}
    ]
  },
  "entity.fault_crawler.emerge": {
    "subtitle": "subtitles.kruemblegard.fault_crawler.emerge",
    "sounds": [
      {"name": "kruemblegard:entity/fault_crawler/emerge"}
    ]
  },

  "entity.scaralon_beetle.ambient": {
    "subtitle": "subtitles.kruemblegard.scaralon_beetle.ambient",
    "sounds": [
      {"name": "kruemblegard:entity/scaralon_beetle/ambient"}
    ]
  },
  "entity.scaralon_beetle.hurt": {
    "subtitle": "subtitles.kruemblegard.scaralon_beetle.hurt",
    "sounds": [
      {"name": "kruemblegard:entity/scaralon_beetle/hurt"}
    ]
  },
  "entity.scaralon_beetle.death": {
    "subtitle": "subtitles.kruemblegard.scaralon_beetle.death",
    "sounds": [
      {"name": "kruemblegard:entity/scaralon_beetle/death"}
    ]
  },
  "entity.scaralon_beetle.step": {
    "subtitle": "subtitles.kruemblegard.scaralon_beetle.step",
    "sounds": [
      {"name": "kruemblegard:entity/scaralon_beetle/step"}
    ]
  },
  "entity.scaralon_beetle.attack": {
    "subtitle": "subtitles.kruemblegard.scaralon_beetle.attack",
    "sounds": [
      {"name": "kruemblegard:entity/scaralon_beetle/attack"}
    ]
  },

  "entity.wyrdwing.ambient": {
    "subtitle": "subtitles.kruemblegard.wyrdwing.ambient",
    "sounds": [
      {"name": "kruemblegard:entity/wyrdwing/ambient"}
    ]
  },
  "entity.wyrdwing.hurt": {
    "subtitle": "subtitles.kruemblegard.wyrdwing.hurt",
    "sounds": [
      {"name": "kruemblegard:entity/wyrdwing/hurt"}
    ]
  },
  "entity.wyrdwing.death": {
    "subtitle": "subtitles.kruemblegard.wyrdwing.death",
    "sounds": [
      {"name": "kruemblegard:entity/wyrdwing/death"}
    ]
  },
  "entity.wyrdwing.step": {
    "subtitle": "subtitles.kruemblegard.wyrdwing.step",
    "sounds": [
      {"name": "kruemblegard:entity/wyrdwing/step"}
    ]
  },
  "entity.wyrdwing.attack": {
    "subtitle": "subtitles.kruemblegard.wyrdwing.attack",
    "sounds": [
      {"name": "kruemblegard:entity/wyrdwing/attack"}
    ]
  },
  "entity.wyrdwing.call": {
    "subtitle": "subtitles.kruemblegard.wyrdwing.call",
    "sounds": [
      {"name": "kruemblegard:entity/wyrdwing/call"}
    ]
  }
}
