{
  "type": "minecraft:random_patch",
  "config": {
    "tries": 18,
    "xz_spread": 6,
    "y_spread": 2,
    "feature": {
      "feature": {
        "type": "minecraft:block_column",
        "config": {
          "allowed_placement": {
            "blocks": "minecraft:air",
            "type": "minecraft:matching_blocks"
          },
          "direction": "up",
          "layers": [
            {
              "height": {
                "value": {
                  "min_inclusive": 3,
                  "max_inclusive": 8
                },
                "type": "minecraft:uniform"
              },
              "provider": {
                "state": {
                  "Name": "kruemblegard:pyrokelp"
                },
                "type": "minecraft:simple_state_provider"
              }
            }
          ],
          "prioritize_tip": false
        }
      },
      "placement": [
        {
          "type": "minecraft:block_predicate_filter",
          "predicate": {
            "type": "minecraft:all_of",
            "predicates": [
              {
                "type": "minecraft:replaceable"
              },
              {
                "type": "minecraft:would_survive",
                "state": {
                  "Name": "kruemblegard:pyrokelp"
                }
              }
            ]
          }
        }
      ]
    }
  }
}
